{"title":"Homefront.2013.720p.HDRip.h264.AAC-RARBG","uid":9552071,"size":2334004304,"categoryP":"video","categoryS":"hd___movies","magnet":"?xt=urn:btih:06ea25bd3ae796de6cfc6425f0d605117be75904&amp;dn=Homefront.2013.720p.HDRip.h264.AAC-RARBG&amp;tr=udp%3A%2F%2Ftracker.openbittorrent.com%3A80&amp;tr=udp%3A%2F%2Fopen.demonii.com%3A1337&amp;tr=udp%3A%2F%2Ftracker.coppersurfer.tk%3A6969&amp;tr=udp%3A%2F%2Fexodus.desync.com%3A6969","seeders":10,"leechers":2,"uploader":"Drarbg","files":2,"time":1391288305,"description":"Homefront.2013.720p.HDRip.h264.AAC-RARBG\n-----------------------------------------\nScreens : &lt;a href=&quot;\nhttp://i.imgur.com/gorcljw.png&quot; rel=&quot;nofollow&quot; target=&quot;_NEW&quot;&gt;\nhttp://i.imgur.com/gorcljw.png&lt;/a&gt; &lt;a href=&quot;\nhttp://i.imgur.com/9feAejq.png&quot; rel=&quot;nofollow&quot; target=&quot;_NEW&quot;&gt;\nhttp://i.imgur.com/9feAejq.png&lt;/a&gt; &lt;a href=&quot;\nhttp://i.imgur.com/svnvjMk.jpg&quot; rel=&quot;nofollow&quot; target=&quot;_NEW&quot;&gt;\nhttp://i.imgur.com/svnvjMk.jpg&lt;/a&gt; &lt;a href=&quot;\nhttp://i.imgur.com/Ni7mOQS.png&quot; rel=&quot;nofollow&quot; target=&quot;_NEW&quot;&gt;\nhttp://i.imgur.com/Ni7mOQS.png&lt;/a&gt; &lt;a href=&quot;\nhttp://i.imgur.com/zHiE5wm.jpg&quot; rel=&quot;nofollow&quot; target=&quot;_NEW&quot;&gt;\nhttp://i.imgur.com/zHiE5wm.jpg&lt;/a&gt; &lt;a href=&quot;\nhttp://i.imgur.com/mm1oYA5.jpg&quot; rel=&quot;nofollow&quot; target=&quot;_NEW&quot;&gt;\nhttp://i.imgur.com/mm1oYA5.jpg&lt;/a&gt;\n\n","torrent":{"xt":"urn:btih:06ea25bd3ae796de6cfc6425f0d605117be75904","amp;dn":"Homefront.2013.720p.HDRip.h264.AAC-RARBG","amp;tr":["udp%3A%2F%2Ftracker.openbittorrent.com%3A80","udp%3A%2F%2Fopen.demonii.com%3A1337","udp%3A%2F%2Ftracker.coppersurfer.tk%3A6969","udp%3A%2F%2Fexodus.desync.com%3A6969"],"infoHash":"06ea25bd3ae796de6cfc6425f0d605117be75904","infoHashBuffer":{"type":"Buffer","data":[6,234,37,189,58,231,150,222,108,252,100,37,240,214,5,17,123,231,89,4]},"announce":[],"urlList":[]}}