{"title":"BrazzersExxtra - Bonnie Rotten, Gia Dimarco - Caught At The Peep","uid":11952839,"size":401570544,"categoryP":"porn","categoryS":"movie_clips","magnet":"?xt=urn:btih:074f6ca6784cc7f9d56787a650234a8edbf56e76&amp;dn=BrazzersExxtra+-+Bonnie+Rotten%2C+Gia+Dimarco+-+Caught+At+The+Peep&amp;tr=udp%3A%2F%2Ftracker.openbittorrent.com%3A80&amp;tr=udp%3A%2F%2Fopen.demonii.com%3A1337&amp;tr=udp%3A%2F%2Ftracker.coppersurfer.tk%3A6969&amp;tr=udp%3A%2F%2Fexodus.desync.com%3A6969","seeders":11,"leechers":13,"uploader":"gemini527nj","files":1,"time":1432239919,"description":"BrazzersExxtra - Bonnie Rotten, Gia Dimarco - Caught At The Peephole (480p_1000)\n\nScreenshots:\n------------ &lt;a href=&quot;\nhttp://image-tpb.com/img-555e22a13edad.html&quot; rel=&quot;nofollow&quot; target=&quot;_NEW&quot;&gt;\nhttp://image-tpb.com/img-555e22a13edad.html&lt;/a&gt;\n &lt;a href=&quot;\nhttp://image-tpb.com/img-555e2380951bc.html&quot; rel=&quot;nofollow&quot; target=&quot;_NEW&quot;&gt;\nhttp://image-tpb.com/img-555e2380951bc.html&lt;/a&gt;","torrent":{"xt":"urn:btih:074f6ca6784cc7f9d56787a650234a8edbf56e76","amp;dn":"BrazzersExxtra+-+Bonnie+Rotten%2C+Gia+Dimarco+-+Caught+At+The+Peep","amp;tr":["udp%3A%2F%2Ftracker.openbittorrent.com%3A80","udp%3A%2F%2Fopen.demonii.com%3A1337","udp%3A%2F%2Ftracker.coppersurfer.tk%3A6969","udp%3A%2F%2Fexodus.desync.com%3A6969"],"infoHash":"074f6ca6784cc7f9d56787a650234a8edbf56e76","infoHashBuffer":{"type":"Buffer","data":[7,79,108,166,120,76,199,249,213,103,135,166,80,35,74,142,219,245,110,118]},"announce":[],"urlList":[]}}