{"title":"Open.Ended.3.XXX.1080P.WEBRIP.MP4-GUSH","uid":12467651,"size":9908244635,"categoryP":"porn","categoryS":"movies","magnet":"?xt=urn:btih:0d0d69570c00577e789635712289acce586e9853&amp;dn=Open.Ended.3.XXX.1080P.WEBRIP.MP4-GUSH&amp;tr=udp%3A%2F%2Ftracker.openbittorrent.com%3A80&amp;tr=udp%3A%2F%2Fopen.demonii.com%3A1337&amp;tr=udp%3A%2F%2Ftracker.coppersurfer.tk%3A6969&amp;tr=udp%3A%2F%2Fexodus.desync.com%3A6969","seeders":11,"leechers":23,"uploader":"0-DayXXX","files":1,"time":1442876168,"description":"---------------------------------------\nOpen.Ended.3.XXX.1080P.WEBRIP.MP4-GUSH\n---------------------------------------\nScreenshot(s): &lt;a href=&quot;\nhttp://imgsay.com/?v=973974.jpg&quot; rel=&quot;nofollow&quot; target=&quot;_NEW&quot;&gt;\nhttp://imgsay.com/?v=973974.jpg&lt;/a&gt;\n\n---------------------------------------\nFormat:\t\tMPEG-4\nSize:\t\t9.23 GiB\nDuration:\t3h 8min\nResolution:\t1920x1080\nBitrate:\t6800Kbps\n---------------------------------------\nIf you like this torrent, please post a comment!\n\nDon't forget to seed!","torrent":{"xt":"urn:btih:0d0d69570c00577e789635712289acce586e9853","amp;dn":"Open.Ended.3.XXX.1080P.WEBRIP.MP4-GUSH","amp;tr":["udp%3A%2F%2Ftracker.openbittorrent.com%3A80","udp%3A%2F%2Fopen.demonii.com%3A1337","udp%3A%2F%2Ftracker.coppersurfer.tk%3A6969","udp%3A%2F%2Fexodus.desync.com%3A6969"],"infoHash":"0d0d69570c00577e789635712289acce586e9853","infoHashBuffer":{"type":"Buffer","data":[13,13,105,87,12,0,87,126,120,150,53,113,34,137,172,206,88,110,152,83]},"announce":[],"urlList":[]}}