{"title":"Through.the.Wormhole.S05E05.Does.the.Ocean.Think.720p.HDTV.x264-","uid":10387873,"size":1279785218,"categoryP":"video","categoryS":"hd___tv_shows","magnet":"?xt=urn:btih:1862f51535bf88f1f37a3b1f3fa856bd72c82697&amp;dn=Through.the.Wormhole.S05E05.Does.the.Ocean.Think.720p.HDTV.x264-&amp;tr=udp%3A%2F%2Ftracker.openbittorrent.com%3A80&amp;tr=udp%3A%2F%2Fopen.demonii.com%3A1337&amp;tr=udp%3A%2F%2Ftracker.coppersurfer.tk%3A6969&amp;tr=udp%3A%2F%2Fexodus.desync.com%3A6969","seeders":11,"leechers":0,"uploader":"Drarbg","files":3,"time":1403154779,"description":"Through.the.Wormhole.S05E05.Does.the.Ocean.Think.720p.HDTV.x264-DHD[rartv]\n-----------------------------------------\nScreens : &lt;a href=&quot;\nhttp://imagecurl.org/viewer.php?file=60517773233619320240.jpg&quot; rel=&quot;nofollow&quot; target=&quot;_NEW&quot;&gt;\nhttp://imagecurl.org/viewer.php?file=60517773233619320240.jpg&lt;/a&gt;\n\n-----------------------------------------\nAuto Media Info :\nVideo Format........: AVC\nCodec ID............: V_MPEG4/ISO/AVC\nLength..............: 42mn56s\nVideo...............: 1280x720 ( 23.976fps )\nBitrate.............: 3510Kbps\nAudio Format........: AC-3\nCodec ID............: A_AC3\nBit rate mode.......: Constant\nBitrate.............: 384Kbps\nChannel(s)..........: 6 channels\n\n","torrent":{"xt":"urn:btih:1862f51535bf88f1f37a3b1f3fa856bd72c82697","amp;dn":"Through.the.Wormhole.S05E05.Does.the.Ocean.Think.720p.HDTV.x264-","amp;tr":["udp%3A%2F%2Ftracker.openbittorrent.com%3A80","udp%3A%2F%2Fopen.demonii.com%3A1337","udp%3A%2F%2Ftracker.coppersurfer.tk%3A6969","udp%3A%2F%2Fexodus.desync.com%3A6969"],"infoHash":"1862f51535bf88f1f37a3b1f3fa856bd72c82697","infoHashBuffer":{"type":"Buffer","data":[24,98,245,21,53,191,136,241,243,122,59,31,63,168,86,189,114,200,38,151]},"announce":[],"urlList":[]}}