{"title":"FIFA.15.DEMO-LEX","uid":11008478,"size":2672008307,"categoryP":"games","categoryS":"pc","magnet":"?xt=urn:btih:186dd26229a7dc0b1373c21f3e81ef78a5ab66c1&amp;dn=FIFA.15.DEMO-LEX&amp;tr=udp%3A%2F%2Ftracker.openbittorrent.com%3A80&amp;tr=udp%3A%2F%2Fopen.demonii.com%3A1337&amp;tr=udp%3A%2F%2Ftracker.coppersurfer.tk%3A6969&amp;tr=udp%3A%2F%2Fexodus.desync.com%3A6969","seeders":10,"leechers":1,"uploader":"dracusorr","files":185,"time":1410292423,"description":"FIFA 15 DEMO","torrent":{"xt":"urn:btih:186dd26229a7dc0b1373c21f3e81ef78a5ab66c1","amp;dn":"FIFA.15.DEMO-LEX","amp;tr":["udp%3A%2F%2Ftracker.openbittorrent.com%3A80","udp%3A%2F%2Fopen.demonii.com%3A1337","udp%3A%2F%2Ftracker.coppersurfer.tk%3A6969","udp%3A%2F%2Fexodus.desync.com%3A6969"],"infoHash":"186dd26229a7dc0b1373c21f3e81ef78a5ab66c1","infoHashBuffer":{"type":"Buffer","data":[24,109,210,98,41,167,220,11,19,115,194,31,62,129,239,120,165,171,102,193]},"announce":[],"urlList":[]}}