{"title":"Fifa 14 SKIDROW (Press And Play)","uid":9150499,"size":7141267367,"categoryP":"games","categoryS":"pc","magnet":"?xt=urn:btih:1dd02724d408dcd75bf0cb4869d73a9ec1c86a36&amp;dn=Fifa+14+SKIDROW+%28Press+And+Play%29&amp;tr=udp%3A%2F%2Ftracker.openbittorrent.com%3A80&amp;tr=udp%3A%2F%2Fopen.demonii.com%3A1337&amp;tr=udp%3A%2F%2Ftracker.coppersurfer.tk%3A6969&amp;tr=udp%3A%2F%2Fexodus.desync.com%3A6969","seeders":11,"leechers":5,"uploader":"tboyx37","files":349,"time":1383683561,"description":"Already Cracked...just click fifa14.exe and play :-)","torrent":{"xt":"urn:btih:1dd02724d408dcd75bf0cb4869d73a9ec1c86a36","amp;dn":"Fifa+14+SKIDROW+%28Press+And+Play%29","amp;tr":["udp%3A%2F%2Ftracker.openbittorrent.com%3A80","udp%3A%2F%2Fopen.demonii.com%3A1337","udp%3A%2F%2Ftracker.coppersurfer.tk%3A6969","udp%3A%2F%2Fexodus.desync.com%3A6969"],"infoHash":"1dd02724d408dcd75bf0cb4869d73a9ec1c86a36","infoHashBuffer":{"type":"Buffer","data":[29,208,39,36,212,8,220,215,91,240,203,72,105,215,58,158,193,200,106,54]},"announce":[],"urlList":[]}}