{"title":"The.Heat.2013.UNRATED.720p.BluRay.DTS.x264-PublicHD","uid":8996681,"size":6201075589,"categoryP":"video","categoryS":"hd___movies","magnet":"?xt=urn:btih:297e1c568c6ac07ecd64e750c315c8dd7f4c57c0&amp;dn=The.Heat.2013.UNRATED.720p.BluRay.DTS.x264-PublicHD&amp;tr=udp%3A%2F%2Ftracker.openbittorrent.com%3A80&amp;tr=udp%3A%2F%2Fopen.demonii.com%3A1337&amp;tr=udp%3A%2F%2Ftracker.coppersurfer.tk%3A6969&amp;tr=udp%3A%2F%2Fexodus.desync.com%3A6969","seeders":11,"leechers":2,"uploader":"BOZX","files":-1,"time":1380879855,"description":"                PublicHD - High-Definition Bittorrent Community\n      \n                           \n    \n              ----------------------------------------------------\n\nThe.Heat.2013.UNRATED.720p.BluRay.DTS.x264-PublicHD\n &lt;a href=&quot;\nhttp://www.imdb.com/title/tt2404463/&quot; rel=&quot;nofollow&quot; target=&quot;_NEW&quot;&gt;\nhttp://www.imdb.com/title/tt2404463/&lt;/a&gt;\n\nDate ...............: October 4 2013\nRuntime ............: 2:00:20\nSize ...............: 5.77 GB\nVideo ..............: 1280x534\nBitrate ............: 4897 kbps (H264 &lt;a class=&quot;__cf_email__&quot; href=&quot;/cdn-cgi/l/email-protection&quot; data-cfemail=&quot;cc84a5aba48c80f8e2fd&quot;&gt;[email&amp;#160;protected]&lt;/a&gt;&lt;script cf-hash='f9e31' type=&quot;text/javascript&quot;&gt;\n/* &lt;![CDATA[ */!function(){try{var t=&quot;currentScript&quot;in document?document.currentScript:function(){for(var t=document.getElementsByTagName(&quot;script&quot;),e=t.length;e--;)if(t[e].getAttribute(&quot;cf-hash&quot;))return t[e]}();if(t&amp;&amp;t.previousSibling){var e,r,n,i,c=t.previousSibling,a=c.getAttribute(&quot;data-cfemail&quot;);if(a){for(e=&quot;&quot;,r=parseInt(a.substr(0,2),16),n=2;a.length-n;n+=2)i=parseInt(a.substr(n,2),16)^r,e+=String.fromCharCode(i);e=document.createTextNode(e),c.parentNode.replaceChild(e,c)}}}catch(u){}}();/* ]]&gt; */&lt;/script&gt; CBR)\nAudio 1.............: English DTS 5.1 Ch 1510 kbps\nChapters............: Yes\nSource .............: 1080p Blu-ray AVC DTS-HD MA 5.1-PublicHD\nSubs ...............: English Spanish French Portuguese Arabic Bulgarian Chinese\n                      Croatian Czech Greek Hebrew Hungarian Icelandic Indonesian \n                      Korean Malay Polish Portuguese Romanian Serrbian Slovenian \n                      Thai Turkish Vietnamese\n\nScreens.............: $39,115,043 (USA) (30 June 2013) (3,181 Screens)\nGenre ..............: Action | Comedy | Crime\n\n\nSCREENS\n &lt;a href=&quot;\nhttp://someimage.com/n82eowL&quot; rel=&quot;nofollow&quot; target=&quot;_NEW&quot;&gt;\nhttp://someimage.com/n82eowL&lt;/a&gt;\n &lt;a href=&quot;\nhttp://someimage.com/deXCqZZ&quot; rel=&quot;nofollow&quot; target=&quot;_NEW&quot;&gt;\nhttp://someimage.com/deXCqZZ&lt;/a&gt;\n &lt;a href=&quot;\nhttp://someimage.com/KLj7UpS&quot; rel=&quot;nofollow&quot; target=&quot;_NEW&quot;&gt;\nhttp://someimage.com/KLj7UpS&lt;/a&gt;\n &lt;a href=&quot;\nhttp://someimage.com/ZWYchsp&quot; rel=&quot;nofollow&quot; target=&quot;_NEW&quot;&gt;\nhttp://someimage.com/ZWYchsp&lt;/a&gt;\n &lt;a href=&quot;\nhttp://someimage.com/flttH5v&quot; rel=&quot;nofollow&quot; target=&quot;_NEW&quot;&gt;\nhttp://someimage.com/flttH5v&lt;/a&gt;\n &lt;a href=&quot;\nhttp://someimage.com/URyXWlq&quot; rel=&quot;nofollow&quot; target=&quot;_NEW&quot;&gt;\nhttp://someimage.com/URyXWlq&lt;/a&gt;\n &lt;a href=&quot;\nhttp://someimage.com/cagNMpL&quot; rel=&quot;nofollow&quot; target=&quot;_NEW&quot;&gt;\nhttp://someimage.com/cagNMpL&lt;/a&gt;\n &lt;a href=&quot;\nhttp://someimage.com/wFtlrin&quot; rel=&quot;nofollow&quot; target=&quot;_NEW&quot;&gt;\nhttp://someimage.com/wFtlrin&lt;/a&gt;\n &lt;a href=&quot;\nhttp://someimage.com/yBDEMXY&quot; rel=&quot;nofollow&quot; target=&quot;_NEW&quot;&gt;\nhttp://someimage.com/yBDEMXY&lt;/a&gt;\n &lt;a href=&quot;\nhttp://someimage.com/kSj4zHS&quot; rel=&quot;nofollow&quot; target=&quot;_NEW&quot;&gt;\nhttp://someimage.com/kSj4zHS&lt;/a&gt;\n","torrent":{"xt":"urn:btih:297e1c568c6ac07ecd64e750c315c8dd7f4c57c0","amp;dn":"The.Heat.2013.UNRATED.720p.BluRay.DTS.x264-PublicHD","amp;tr":["udp%3A%2F%2Ftracker.openbittorrent.com%3A80","udp%3A%2F%2Fopen.demonii.com%3A1337","udp%3A%2F%2Ftracker.coppersurfer.tk%3A6969","udp%3A%2F%2Fexodus.desync.com%3A6969"],"infoHash":"297e1c568c6ac07ecd64e750c315c8dd7f4c57c0","infoHashBuffer":{"type":"Buffer","data":[41,126,28,86,140,106,192,126,205,100,231,80,195,21,200,221,127,76,87,192]},"announce":[],"urlList":[]}}