{"title":"New Jersey Drive (1995) Best Hood Movie Ever [Divx3-Lm].avi","uid":3345658,"size":722905088,"categoryP":"video","categoryS":"movies","magnet":"?xt=urn:btih:385fbdd68ba4a38371c12db55ad8e31f269d03cb&amp;dn=New+Jersey+Drive+%281995%29+Best+Hood+Movie+Ever+%5BDivx3-Lm%5D.avi&amp;tr=udp%3A%2F%2Ftracker.openbittorrent.com%3A80&amp;tr=udp%3A%2F%2Fopen.demonii.com%3A1337&amp;tr=udp%3A%2F%2Ftracker.coppersurfer.tk%3A6969&amp;tr=udp%3A%2F%2Fexodus.desync.com%3A6969","seeders":13,"leechers":1,"uploader":"rci","files":1,"time":1119034510,"description":"Two young black teenagers living in Newark New Jersey the unofficial car theft capital of the world. Their favourite pastime is that of everybody in their neighbourhood stealing cars and joyriding. The trouble starts when they steal a police car and the cops launch a violent offensive that involves beating and even shooting suspects...","torrent":{"xt":"urn:btih:385fbdd68ba4a38371c12db55ad8e31f269d03cb","amp;dn":"New+Jersey+Drive+%281995%29+Best+Hood+Movie+Ever+%5BDivx3-Lm%5D.avi","amp;tr":["udp%3A%2F%2Ftracker.openbittorrent.com%3A80","udp%3A%2F%2Fopen.demonii.com%3A1337","udp%3A%2F%2Ftracker.coppersurfer.tk%3A6969","udp%3A%2F%2Fexodus.desync.com%3A6969"],"infoHash":"385fbdd68ba4a38371c12db55ad8e31f269d03cb","infoHashBuffer":{"type":"Buffer","data":[56,95,189,214,139,164,163,131,113,193,45,181,90,216,227,31,38,157,3,203]},"announce":[],"urlList":[]}}