{"title":"Once Upon a Time S01E18 HDTV XviD-AFG[ettv]","uid":7151885,"size":363715920,"categoryP":"video","categoryS":"tv_shows","magnet":"?xt=urn:btih:468d7027a31fe748ed12367e764df4009d9defed&amp;dn=Once+Upon+a+Time+S01E18+HDTV+XviD-AFG%5Bettv%5D&amp;tr=udp%3A%2F%2Ftracker.openbittorrent.com%3A80&amp;tr=udp%3A%2F%2Fopen.demonii.com%3A1337&amp;tr=udp%3A%2F%2Ftracker.coppersurfer.tk%3A6969&amp;tr=udp%3A%2F%2Fexodus.desync.com%3A6969","seeders":11,"leechers":0,"uploader":"ettv","files":3,"time":1333331343,"description":"Once.Upon.a.Time.S01E18.HDTV.XviD-AFG Once.Upon.a.Time.S01E18.HDTV.XviD-AFG.avi\n\nDuration: 43 Minutes\nRelease Size: 347MB\nXviD Video: 984 Kbps\nFrameRate: 23.976\nMP3 2ch CBR: 128 Kbps\nResolution (AR): 640x360 (1.778)","torrent":{"xt":"urn:btih:468d7027a31fe748ed12367e764df4009d9defed","amp;dn":"Once+Upon+a+Time+S01E18+HDTV+XviD-AFG%5Bettv%5D","amp;tr":["udp%3A%2F%2Ftracker.openbittorrent.com%3A80","udp%3A%2F%2Fopen.demonii.com%3A1337","udp%3A%2F%2Ftracker.coppersurfer.tk%3A6969","udp%3A%2F%2Fexodus.desync.com%3A6969"],"infoHash":"468d7027a31fe748ed12367e764df4009d9defed","infoHashBuffer":{"type":"Buffer","data":[70,141,112,39,163,31,231,72,237,18,54,126,118,77,244,0,157,157,239,237]},"announce":[],"urlList":[]}}