{"title":"Frequency.S01E02.720p.HEVC.x265-MeGusta","uid":16021364,"size":201581958,"categoryP":"video","categoryS":"tv_shows","magnet":"?xt=urn:btih:471242809a5021aab51429eedc23c9058ea3e09c&amp;dn=Frequency.S01E02.720p.HEVC.x265-MeGusta&amp;tr=udp%3A%2F%2Ftracker.leechers-paradise.org%3A6969&amp;tr=udp%3A%2F%2Fzer0day.ch%3A1337&amp;tr=udp%3A%2F%2Fopen.demonii.com%3A1337&amp;tr=udp%3A%2F%2Ftracker.coppersurfer.tk%3A6969&amp;tr=udp%3A%2F%2Fexodus.desync.com%3A6969","seeders":10,"leechers":2,"uploader":"TvTeam","files":7,"time":1476335722,"description":"Torrent from:\r\n~~~~~~~~~~~~~~~~ \nhttps://www.torrenting.com\r\n\r\nJoin us and become part of the BIG family! Yarrrrrrrrrrrrrr!!!","torrent":{"xt":"urn:btih:471242809a5021aab51429eedc23c9058ea3e09c","amp;dn":"Frequency.S01E02.720p.HEVC.x265-MeGusta","amp;tr":["udp%3A%2F%2Ftracker.leechers-paradise.org%3A6969","udp%3A%2F%2Fzer0day.ch%3A1337","udp%3A%2F%2Fopen.demonii.com%3A1337","udp%3A%2F%2Ftracker.coppersurfer.tk%3A6969","udp%3A%2F%2Fexodus.desync.com%3A6969"],"infoHash":"471242809a5021aab51429eedc23c9058ea3e09c","infoHashBuffer":{"type":"Buffer","data":[71,18,66,128,154,80,33,170,181,20,41,238,220,35,201,5,142,163,224,156]},"announce":[],"urlList":[]}}