{"title":"Stephen King - Doctor Sleep (Audiobook) MP3 &amp; M4B","uid":8965121,"size":827493441,"categoryP":"audio","categoryS":"audio_books","magnet":"?xt=urn:btih:49bf5c782d16016f86a47e097585e9b40fafafdd&amp;dn=Stephen+King+-+Doctor+Sleep+%28Audiobook%29+MP3+%26amp%3B+M4B&amp;tr=udp%3A%2F%2Ftracker.openbittorrent.com%3A80&amp;tr=udp%3A%2F%2Fopen.demonii.com%3A1337&amp;tr=udp%3A%2F%2Ftracker.coppersurfer.tk%3A6969&amp;tr=udp%3A%2F%2Fexodus.desync.com%3A6969","seeders":11,"leechers":2,"uploader":"RedJohn81","files":6,"time":1380202697,"description":"Found through another source.\nRetagged and edited with album artwork and presenting in MP3 and M4B (iTunes audiobook format for those who are interested).\nThis is my first upload here so please enjoy :)","torrent":{"xt":"urn:btih:49bf5c782d16016f86a47e097585e9b40fafafdd","amp;dn":"Stephen+King+-+Doctor+Sleep+%28Audiobook%29+MP3+%26amp%3B+M4B","amp;tr":["udp%3A%2F%2Ftracker.openbittorrent.com%3A80","udp%3A%2F%2Fopen.demonii.com%3A1337","udp%3A%2F%2Ftracker.coppersurfer.tk%3A6969","udp%3A%2F%2Fexodus.desync.com%3A6969"],"infoHash":"49bf5c782d16016f86a47e097585e9b40fafafdd","infoHashBuffer":{"type":"Buffer","data":[73,191,92,120,45,22,1,111,134,164,126,9,117,133,233,180,15,175,175,221]},"announce":[],"urlList":[]}}