{"title":"The Game S07E02 HDTV x264-2HD [eztv]","uid":9747032,"size":172340265,"categoryP":"video","categoryS":"tv_shows","magnet":"?xt=urn:btih:6ea502ecd689fe14f5513b5876c146905d578589&amp;dn=The+Game+S07E02+HDTV+x264-2HD+%5Beztv%5D&amp;tr=udp%3A%2F%2Ftracker.openbittorrent.com%3A80&amp;tr=udp%3A%2F%2Fopen.demonii.com%3A1337&amp;tr=udp%3A%2F%2Ftracker.coppersurfer.tk%3A6969&amp;tr=udp%3A%2F%2Fexodus.desync.com%3A6969","seeders":12,"leechers":2,"uploader":"eztv","files":1,"time":1394598821,"description":"Help us by donating with Bitcoin: 1EZTVaGQ6UsjYJ9fwqGnd45oZ6HGT7WKZd\n\n#EZTV -&gt; To avoid fakes, ALWAYS check that the torrent was added by eztv.\n &lt;a href=&quot;\nhttps://eztv.it/&quot; rel=&quot;nofollow&quot; target=&quot;_NEW&quot;&gt;\nhttps://eztv.it/&lt;/a&gt;\n\nEpisode: The Game S07E02 HDTV x264-2HD\nScreenshots:\n\n\n","torrent":{"xt":"urn:btih:6ea502ecd689fe14f5513b5876c146905d578589","amp;dn":"The+Game+S07E02+HDTV+x264-2HD+%5Beztv%5D","amp;tr":["udp%3A%2F%2Ftracker.openbittorrent.com%3A80","udp%3A%2F%2Fopen.demonii.com%3A1337","udp%3A%2F%2Ftracker.coppersurfer.tk%3A6969","udp%3A%2F%2Fexodus.desync.com%3A6969"],"infoHash":"6ea502ecd689fe14f5513b5876c146905d578589","infoHashBuffer":{"type":"Buffer","data":[110,165,2,236,214,137,254,20,245,81,59,88,118,193,70,144,93,87,133,137]},"announce":[],"urlList":[]}}