{"title":"Gilda (1946) 720p BrRip x264 - VPPV","uid":13373304,"size":885216298,"categoryP":"video","categoryS":"hd___movies","magnet":"?xt=urn:btih:6eabab4c948f66e7d8281965b3a11d0f5010cd99&amp;dn=Gilda+%281946%29+720p+BrRip+x264+-+VPPV&amp;tr=udp%3A%2F%2Ftracker.leechers-paradise.org%3A6969&amp;tr=udp%3A%2F%2Fzer0day.ch%3A1337&amp;tr=udp%3A%2F%2Fopen.demonii.com%3A1337&amp;tr=udp%3A%2F%2Ftracker.coppersurfer.tk%3A6969&amp;tr=udp%3A%2F%2Fexodus.desync.com%3A6969","seeders":10,"leechers":0,"uploader":"VPPV","files":3,"time":1454205926,"description":"IMDB:  \nhttp://www.imdb.com/title/tt0038559/                \r\n\r\nDescription:\r\nJust arrived in Argentina, small-time crooked gambler Johnny Farrell is saved from a gunman by sinister Ballin Mundson, who later makes Johnny his right-hand man. But their friendship based on mutual lack of scruples is strained when Mundson returns from a trip with a wife: the supremely desirable Gilda, whom Johnny once knew and learned to hate. The relationship of Johnny and Gilda, a battlefield of warring emotions, becomes even more bizarre after Mundson disappears...                \r\n\r\nYear: 1946                \r\nDirector: Charles Vidor                \r\nWriters: E.A. Ellington, Jo Eisinger, Marion Parsonnet, Ben Hecht                \r\nStars: Rita Hayworth, Glenn Ford, George Macready, Joseph Calleia, Steven Geray, Joe Sawyer, Gerald Mohr, Mark Roberts, Ludwig Donath, Donald Douglas                \r\nGenres: Drama, Film-Noir, Romance, Thriller                \r\nLanguage: English                \r\n\r\nRELEASE.....................: Gilda.1946.720p.BluRay.x264.VPPV\r\nVIDEO.......................: 1000 kbps  \r\nCODEC.......................: x264\r\nRESOLUTION..................: 800x600                \r\nFRAME RATE..................: 23.976 fps\r\nAUDIO.......................: 2 Channel / HE-AAC(FDK) / 128kbps                \r\nFILE SIZE / FORMAT..........: 844MB / MP4\r\nSOURCE......................: BluRay                \r\n\r\n\r\n-------------------------------------------------------------------------------\r\n\r\n\r\nPoster:  \nhttp://snap.vppv.la/gilda/1946/gilda-1946-poster.jpg               \r\n\r\nWarning!!! Images may contain spoilers!!!\r\n\r\nScreenshot 1:  \nhttp://snap.vppv.la/gilda/1946/720p/snap1.jpg               \r\nScreenshot 2:  \nhttp://snap.vppv.la/gilda/1946/720p/snap2.jpg               \r\nScreenshot 3:  \nhttp://snap.vppv.la/gilda/1946/720p/snap3.jpg","torrent":{"xt":"urn:btih:6eabab4c948f66e7d8281965b3a11d0f5010cd99","amp;dn":"Gilda+%281946%29+720p+BrRip+x264+-+VPPV","amp;tr":["udp%3A%2F%2Ftracker.leechers-paradise.org%3A6969","udp%3A%2F%2Fzer0day.ch%3A1337","udp%3A%2F%2Fopen.demonii.com%3A1337","udp%3A%2F%2Ftracker.coppersurfer.tk%3A6969","udp%3A%2F%2Fexodus.desync.com%3A6969"],"infoHash":"6eabab4c948f66e7d8281965b3a11d0f5010cd99","infoHashBuffer":{"type":"Buffer","data":[110,171,171,76,148,143,102,231,216,40,25,101,179,161,29,15,80,16,205,153]},"announce":[],"urlList":[]}}