{"title":"Grand_Funk_Railroad-Greatest_Hits-(Retail)-2006-HHI","uid":8656527,"size":117923350,"categoryP":"audio","categoryS":"music","magnet":"?xt=urn:btih:726780508814fbabdfd0a7b3bd93115cbd2fda39&amp;dn=Grand_Funk_Railroad-Greatest_Hits-%28Retail%29-2006-HHI&amp;tr=udp%3A%2F%2Ftracker.openbittorrent.com%3A80&amp;tr=udp%3A%2F%2Fopen.demonii.com%3A1337&amp;tr=udp%3A%2F%2Ftracker.coppersurfer.tk%3A6969&amp;tr=udp%3A%2F%2Fexodus.desync.com%3A6969","seeders":10,"leechers":1,"uploader":"raidy","files":17,"time":1373228938,"description":"Artist......: Grand funk railroad\nAlbum.......: Greatest hits\nGrabber     : EAC (secure mode rip!)\nEncoder.....: LAME v3.90.3 --alt-preset standard\nRelease Date: Apr-04-2006\nRip Date....: Jul-07-2013\nRipped by...: [HHI] - Happy Hacker Industries - [HHI]\nGenre.......: Rock\nQuality     : VBRkbps / 44.1kHz / Joint-Stereo\nPlaytime    : 69:44 min\nCD Songs    : 14\nLabel.......: Capitol\nReleaseNotes:\n\nThis is the definitive single CD of Grand Fuks greatest hits. CD includes 14 classic hits and signature songs, featuring 9 top 40 hits, including the # Pop Chart hits 'We're An American Band' and 'The Loco-Motion'. Capitol. 2006.\n\n*Remastered*\n\nAlbum opinion is taken from sites such as cduniverse and allmusic.\nHHI has no opinion with regard to the quality of the Artist.\nWe hope you enjoy the music whatever it is!\n\n\nTrack Listing....:\n01.We're an american band                               [03:27]\n02.Time machine                                         [03:45]\n03.Walk like A man                                      [04:05]\n04.Some kind of wonderful                               [03:23]\n05.Shinin' on                                           [05:56]\n06.Heartbreaker                                         [06:35]\n07.Rock 'n roll soul                                    [03:30]\n08.The loco-Motion                                      [02:47]\n09.Footstompin' music                                   [03:47]\n10.Mean mistreater (live)                               [04:56]\n11.Take me                                              [05:06]\n12.Bad time                                             [02:56]\n13.I'm your captain                                     [10:00]\n14.Inside looking out                                   [09:31]\n________\n69:44 min\n112,5 MB\n\nGREETS\n\nEveryone that has supported us over the years.  You know who you are.\nStill Rocking strong!","torrent":{"xt":"urn:btih:726780508814fbabdfd0a7b3bd93115cbd2fda39","amp;dn":"Grand_Funk_Railroad-Greatest_Hits-%28Retail%29-2006-HHI","amp;tr":["udp%3A%2F%2Ftracker.openbittorrent.com%3A80","udp%3A%2F%2Fopen.demonii.com%3A1337","udp%3A%2F%2Ftracker.coppersurfer.tk%3A6969","udp%3A%2F%2Fexodus.desync.com%3A6969"],"infoHash":"726780508814fbabdfd0a7b3bd93115cbd2fda39","infoHashBuffer":{"type":"Buffer","data":[114,103,128,80,136,20,251,171,223,208,167,179,189,147,17,92,189,47,218,57]},"announce":[],"urlList":[]}}