{"title":"22 Jump Street 2014 CAM NEW AUDIO x264 AC3-MiLLENiUM","uid":10411676,"size":1320582938,"categoryP":"video","categoryS":"movies","magnet":"?xt=urn:btih:95a17d6751b65c3c9ca5cccb5ee9d8cf8aaace4c&amp;dn=22+Jump+Street+2014+CAM+NEW+AUDIO+x264+AC3-MiLLENiUM&amp;tr=udp%3A%2F%2Ftracker.openbittorrent.com%3A80&amp;tr=udp%3A%2F%2Fopen.demonii.com%3A1337&amp;tr=udp%3A%2F%2Ftracker.coppersurfer.tk%3A6969&amp;tr=udp%3A%2F%2Fexodus.desync.com%3A6969","seeders":10,"leechers":4,"uploader":"harks88","files":-1,"time":1403546437,"description":"After making their way through high school (twice), big changes are in store for officers Schmidt and Jenko when they go deep undercover at a local college.\n\nSize: 1267884128 bytes (1.18 GiB), duration: 01:39:42, avg.bitrate: 1696 kb/s\nAudio: ac3, 48000 Hz, stereo (eng)\nVideo: h264, yuv420p, 720x320, 29.97 fps(r)\n\n-------------------------------------------------------------------------------------\n\nScreens:\n &lt;a href=&quot;\nhttp://www.imglooks.com/viewer.php?file=49469506421735481818.jpg&quot; rel=&quot;nofollow&quot; target=&quot;_NEW&quot;&gt;\nhttp://www.imglooks.com/viewer.php?file=49469506421735481818.jpg&lt;/a&gt;\n &lt;a href=&quot;\nhttp://www.imglooks.com/viewer.php?file=17439233948129411030.jpg&quot; rel=&quot;nofollow&quot; target=&quot;_NEW&quot;&gt;\nhttp://www.imglooks.com/viewer.php?file=17439233948129411030.jpg&lt;/a&gt;\n &lt;a href=&quot;\nhttp://www.imglooks.com/viewer.php?file=07825079379125581189.jpg&quot; rel=&quot;nofollow&quot; target=&quot;_NEW&quot;&gt;\nhttp://www.imglooks.com/viewer.php?file=07825079379125581189.jpg&lt;/a&gt;\n &lt;a href=&quot;\nhttp://www.imglooks.com/viewer.php?file=21566006131457106583.jpg&quot; rel=&quot;nofollow&quot; target=&quot;_NEW&quot;&gt;\nhttp://www.imglooks.com/viewer.php?file=21566006131457106583.jpg&lt;/a&gt;","torrent":{"xt":"urn:btih:95a17d6751b65c3c9ca5cccb5ee9d8cf8aaace4c","amp;dn":"22+Jump+Street+2014+CAM+NEW+AUDIO+x264+AC3-MiLLENiUM","amp;tr":["udp%3A%2F%2Ftracker.openbittorrent.com%3A80","udp%3A%2F%2Fopen.demonii.com%3A1337","udp%3A%2F%2Ftracker.coppersurfer.tk%3A6969","udp%3A%2F%2Fexodus.desync.com%3A6969"],"infoHash":"95a17d6751b65c3c9ca5cccb5ee9d8cf8aaace4c","infoHashBuffer":{"type":"Buffer","data":[149,161,125,103,81,182,92,60,156,165,204,203,94,233,216,207,138,170,206,76]},"announce":[],"urlList":[]}}