{"title":"The Nice Guys (2016) 720p WebRip x264 English AAC - Moviesland","uid":15463360,"size":713910543,"categoryP":"video","categoryS":"movies","magnet":"?xt=urn:btih:9b1850306c29a29b3e100a76c0af9b01a5d2f59e&amp;dn=The+Nice+Guys+%282016%29+720p+WebRip+x264+English+AAC+-+Moviesland&amp;tr=udp%3A%2F%2Ftracker.leechers-paradise.org%3A6969&amp;tr=udp%3A%2F%2Fzer0day.ch%3A1337&amp;tr=udp%3A%2F%2Fopen.demonii.com%3A1337&amp;tr=udp%3A%2F%2Ftracker.coppersurfer.tk%3A6969&amp;tr=udp%3A%2F%2Fexodus.desync.com%3A6969","seeders":10,"leechers":0,"uploader":"moveez","files":2,"time":1470070435,"description":"IMDB Link:\r\n \nhttp://www.imdb.com/title/tt3799694/\r\n\r\nStoryline:\r\n\r\nA mismatched pair of private eyes investigate the apparent suicide of a porn star in 1970s Los Angeles.\r\n\r\nMedia Info:\r\n\r\nName...........: The Nice Guys (2016)\r\nGenre..........: Action, Comedy, Crime\r\nSize...........: 674 MiB\r\nDuration.......: 1h 51mn\r\nFormat.........: MKV\r\nCodec..........: x264\r\nWidth..........: 1 280 pixels\r\nHeight.........: 528 pixels\r\nAspect ratio...: 2.40:1\r\nFrame rate.....: 25.000 fps\r\nLanguage.......: English\r\nDefault........: English\r\nFormat.........: AAC\r\nSubtiitle......: Null\r\nSource.........: FGT\r\nEncoded By.....: Moviesland\r\n\r\nDownload Sample From The Following Link Or From Torrent:\r\n\r\n\r\nScreens:\r\n \nhttp://emageland.com/image/6","torrent":{"xt":"urn:btih:9b1850306c29a29b3e100a76c0af9b01a5d2f59e","amp;dn":"The+Nice+Guys+%282016%29+720p+WebRip+x264+English+AAC+-+Moviesland","amp;tr":["udp%3A%2F%2Ftracker.leechers-paradise.org%3A6969","udp%3A%2F%2Fzer0day.ch%3A1337","udp%3A%2F%2Fopen.demonii.com%3A1337","udp%3A%2F%2Ftracker.coppersurfer.tk%3A6969","udp%3A%2F%2Fexodus.desync.com%3A6969"],"infoHash":"9b1850306c29a29b3e100a76c0af9b01a5d2f59e","infoHashBuffer":{"type":"Buffer","data":[155,24,80,48,108,41,162,155,62,16,10,118,192,175,155,1,165,210,245,158]},"announce":[],"urlList":[]}}