{"title":"Crazy Chicken Kart 2 [English][PC]","uid":3726509,"size":153893279,"categoryP":"games","categoryS":"pc","magnet":"?xt=urn:btih:d2a3a360af23063d36af88633162980a3e489a09&amp;dn=Crazy+Chicken+Kart+2+%5BEnglish%5D%5BPC%5D&amp;tr=udp%3A%2F%2Ftracker.openbittorrent.com%3A80&amp;tr=udp%3A%2F%2Fopen.demonii.com%3A1337&amp;tr=udp%3A%2F%2Ftracker.coppersurfer.tk%3A6969&amp;tr=udp%3A%2F%2Fexodus.desync.com%3A6969","seeders":10,"leechers":0,"uploader":"torrentscwb","files":13,"time":1183005670,"description":"A funny chicken&amp;#039;s race. Kids love it.","torrent":{"xt":"urn:btih:d2a3a360af23063d36af88633162980a3e489a09","amp;dn":"Crazy+Chicken+Kart+2+%5BEnglish%5D%5BPC%5D","amp;tr":["udp%3A%2F%2Ftracker.openbittorrent.com%3A80","udp%3A%2F%2Fopen.demonii.com%3A1337","udp%3A%2F%2Ftracker.coppersurfer.tk%3A6969","udp%3A%2F%2Fexodus.desync.com%3A6969"],"infoHash":"d2a3a360af23063d36af88633162980a3e489a09","infoHashBuffer":{"type":"Buffer","data":[210,163,163,96,175,35,6,61,54,175,136,99,49,98,152,10,62,72,154,9]},"announce":[],"urlList":[]}}