{"title":"Borderline Personality Disorder For Dummies [PDF]","uid":9776066,"size":2403094,"categoryP":"other","categoryS":"e_books","magnet":"?xt=urn:btih:d69b3d04e61114ffbd68afe6409603c379ba099f&amp;dn=Borderline+Personality+Disorder+For+Dummies+%5BPDF%5D&amp;tr=udp%3A%2F%2Ftracker.openbittorrent.com%3A80&amp;tr=udp%3A%2F%2Fopen.demonii.com%3A1337&amp;tr=udp%3A%2F%2Ftracker.coppersurfer.tk%3A6969&amp;tr=udp%3A%2F%2Fexodus.desync.com%3A6969","seeders":10,"leechers":1,"uploader":"theBooks","files":-1,"time":1395035521,"description":"\n &lt;a href=&quot;\nhttp://s25.postimg.org/8bol1yxun/Borderline_Personality_Disorder_For_Dummies.jpg&quot; rel=&quot;nofollow&quot; target=&quot;_NEW&quot;&gt;\nhttp://s25.postimg.org/8bol1yxun/Borderline_Personality_Disorder_For_Dummies.jpg&lt;/a&gt;\n\nCharles H. Elliott | 2009 | 387 Pages | PDF | English | ISBN-13: 978-0470466537 | 2.29 MB\n\n-----------------------------------------------------------------------------------\n-----------------------------------------------------------------------------------\n\nDescription:\n\n-----------------------------------------------------------------------------------\n-----------------------------------------------------------------------------------\n\nYour clear, compassionate guide to managing BPD -- and living well.\n\nLooking for straightforward information on Borderline Personality Disorder? This easy-to-understand guide helps those who have BPD develop strategies for breaking the destructive cycle. This book also aids loved ones in accepting the disorder and offering support. Inside you'll find authoritative details on the causes of BPD and proven treatments, as well as advice on working with therapists, managing symptoms, and enjoying a full life.\n\n* Review the basics of BPD -- discover the symptoms of BPD and the related emotional problems, as well as the cultural, biological, and psychological causes of the disease\n* Understand what goes wrong -- explore impulsivity, emotional dysregulation, identity problems, relationship conflicts, black-and-white thinking, and difficulties in perception; and identify the areas where you may need help\n* Make the choice to change -- find the right care provider, overcome common obstacles to change, set realistic goals, and improve your physical and emotional state\n* Evaluate treatments for BPD -- learn about the current treatments that really work and develop a plan for addressing the core symptoms of BPD\n* If someone you love has BPD -- see how to identify triggers, handle emotional upheavals, set clear boundaries, and encourage your loved one to seek therapy\n\nOpen the book and find:\n\n* The major characteristics of BPD\n* Who gets BPD -- and why\n* Recent treatment advances\n* Illuminating case studies\n* Strategies for calming emotions and staying in control\n* A discussion of medication options\n* Ways to stay healthy during treatment\n* Tips for explaining BPD to others\n* Help for parents whose child exhibits symptoms\n* Treatment options that work and those you should avoid\n\n-----------------------------------------------------------------------------------\n-----------------------------------------------------------------------------------\n\nAbout the Author/s:\n\n-----------------------------------------------------------------------------------\n-----------------------------------------------------------------------------------\n\nCharles H. Elliott, PhD, and Laura L. Smith, PhD, are clinical psychologists who specialize in training mental health professionals in the treatment of adolescents and adults with personality disorders, as well as obsessive-compulsive disorder, anxiety, anger, and depression. They are the coauthors of Depression For Dummies, Obsessive-Compulsive Disorder For Dummies, and Overcoming Anxiety For Dummies.\n\n-----------------------------------------------------------------------------------\n-----------------------------------------------------------------------------------\n\nNo Password or Surveys. Guaranteed!!!\n\nPlease seed the torrent if you want to Help :)\n\n\n-----------------------------------------------------------------------------------\n-----------------------------------------------------------------------------------","torrent":{"xt":"urn:btih:d69b3d04e61114ffbd68afe6409603c379ba099f","amp;dn":"Borderline+Personality+Disorder+For+Dummies+%5BPDF%5D","amp;tr":["udp%3A%2F%2Ftracker.openbittorrent.com%3A80","udp%3A%2F%2Fopen.demonii.com%3A1337","udp%3A%2F%2Ftracker.coppersurfer.tk%3A6969","udp%3A%2F%2Fexodus.desync.com%3A6969"],"infoHash":"d69b3d04e61114ffbd68afe6409603c379ba099f","infoHashBuffer":{"type":"Buffer","data":[214,155,61,4,230,17,20,255,189,104,175,230,64,150,3,195,121,186,9,159]},"announce":[],"urlList":[]}}