{"title":"Rockstar - DVDRip - 720p - x264 - [DDR]","uid":7023714,"size":3786449981,"categoryP":"video","categoryS":"hd___movies","magnet":"?xt=urn:btih:e41758a6db865385a74893502239b590a4f4bee3&amp;dn=Rockstar+-+DVDRip+-+720p+-+x264+-+%5BDDR%5D&amp;tr=udp%3A%2F%2Ftracker.openbittorrent.com%3A80&amp;tr=udp%3A%2F%2Fopen.demonii.com%3A1337&amp;tr=udp%3A%2F%2Ftracker.coppersurfer.tk%3A6969&amp;tr=udp%3A%2F%2Fexodus.desync.com%3A6969","seeders":11,"leechers":7,"uploader":"SaM","files":-1,"time":1328935613,"description":"Ripper........[ -=KaMaL=-      ]\nRelease Date..[ 10/02/2012     ]\nRuntime.......[ 2:40:00        ]\nResolution....[ 1280 x 544     ]\nFramerate.....[ 23.976 FPS     ]\nSize..........[ 3.50 GB        ]\n                                \nVideo Codec...[ x264           ]\nVideo Bitrate.[ 2700 Kb/s      ]\nAudio Info....[ 448Kbps DD 5.1 ]\nAudio Language[ Hindi          ]\nSubtitles.....[ English,Arabic.]\n                                \nContainer.....[ MKV            ]\n                                \n                                \n    Thanks RK, U Rock Bro..!    \n                                \n                                \n   !..The Exclusive Encode..!   \n                                \n          Enjoy   !!!           \n\n\n Cast :   Ranbir Kapoor        Piyush Mishra     \n          Nargis Fakhri        Moufid Aziz       \n          Shammi Kapoor        Kumud Mishra      \n          Shikha Jain          Shernaz Patel     \n          Jaideep Ahlawat      Aditi Rao Hydari  \n                                                 \n                                                 \n                                                 \n       Director    :    Imtiaz Ali               \n       Writer      :    Imtiaz Ali               \n                                                 \n       Genre       :    Comedy | Drama | Music   \n                                                 \n                                                 \n Dressed in Persian clothes, chased by hooligans,\n famous Indian-born Rockstar, Jordan, barely     \n makes it to a Czech stadium to perform before   \n a huge crowd. It was not too long ago that he   \n was just an awkward uninhibited collegian       \n wanna-be musician with a name of Janardhan      \n Jakhar, who was ridiculed everywhere. His       \n family wanted him to be inducted in their       \n business but he refuses. He is counseled that   \n music comes after experiencing pain, so he      \n decides to woo Heer Kaul, the hottest girl      \n on the college's 'Chicklist' in order to be     \n rejected by her and thus experience pain.       \n Initially he does face rejection from the       \n sophisticated and cultured Heer, but quite      \n surprisingly they subsequently become close     \n friends, and he finds that underneath the stiff \n upper lip, there is a woman who is full of life \n                                                 \n   IMDB Link :                                   \n                                                 \n      &lt;a href=&quot; http://www.imdb.com/title/tt1839596/&quot; rel=&quot;nofollow&quot; target=&quot;_NEW&quot;&gt; http://www.imdb.com/title/tt1839596/&lt;/a&gt;      \n                                                 \n              Users Rating : 7.5/10              \n\n &lt;a href=&quot;\nhttp://server1.upload-novalayer.com/files/4/fwdkyr1xe51t54/1.png&quot; rel=&quot;nofollow&quot; target=&quot;_NEW&quot;&gt;\nhttp://server1.upload-novalayer.com/files/4/fwdkyr1xe51t54/1.png&lt;/a&gt;  &lt;a href=&quot;\nhttp://server1.upload-novalayer.com/files/5/xhjbhrncmtxc06/2.png&quot; rel=&quot;nofollow&quot; target=&quot;_NEW&quot;&gt;\nhttp://server1.upload-novalayer.com/files/5/xhjbhrncmtxc06/2.png&lt;/a&gt;  &lt;a href=&quot;\nhttp://server1.upload-novalayer.com/files/8/695hgw9xw2iip5/3.png&quot; rel=&quot;nofollow&quot; target=&quot;_NEW&quot;&gt;\nhttp://server1.upload-novalayer.com/files/8/695hgw9xw2iip5/3.png&lt;/a&gt;  &lt;a href=&quot;\nhttp://server1.upload-novalayer.com/files/3/gmfydlp7pvhnwz/4.png&quot; rel=&quot;nofollow&quot; target=&quot;_NEW&quot;&gt;\nhttp://server1.upload-novalayer.com/files/3/gmfydlp7pvhnwz/4.png&lt;/a&gt;  &lt;a href=&quot;\nhttp://server1.upload-novalayer.com/files/9/s1005d9m26e2hh/5.png&quot; rel=&quot;nofollow&quot; target=&quot;_NEW&quot;&gt;\nhttp://server1.upload-novalayer.com/files/9/s1005d9m26e2hh/5.png&lt;/a&gt;  &lt;a href=&quot;\nhttp://server1.upload-novalayer.com/files/8/cvaquqd46sk22x/6.png&quot; rel=&quot;nofollow&quot; target=&quot;_NEW&quot;&gt;\nhttp://server1.upload-novalayer.com/files/8/cvaquqd46sk22x/6.png&lt;/a&gt;  &lt;a href=&quot;\nhttp://server1.upload-novalayer.com/files/7/tkrxjtqbhuj81z/7.png&quot; rel=&quot;nofollow&quot; target=&quot;_NEW&quot;&gt;\nhttp://server1.upload-novalayer.com/files/7/tkrxjtqbhuj81z/7.png&lt;/a&gt;  &lt;a href=&quot;\nhttp://server1.upload-novalayer.com/files/5/8nthmq9thw1zhp/8.png&quot; rel=&quot;nofollow&quot; target=&quot;_NEW&quot;&gt;\nhttp://server1.upload-novalayer.com/files/5/8nthmq9thw1zhp/8.png&lt;/a&gt;  &lt;a href=&quot;\nhttp://server1.upload-novalayer.com/files/8/yc4xasrfccmsh7/9.png&quot; rel=&quot;nofollow&quot; target=&quot;_NEW&quot;&gt;\nhttp://server1.upload-novalayer.com/files/8/yc4xasrfccmsh7/9.png&lt;/a&gt;  &lt;a href=&quot;\nhttp://server1.upload-novalayer.com/files/6/2andwqmcch1zt3/10.png&quot; rel=&quot;nofollow&quot; target=&quot;_NEW&quot;&gt;\nhttp://server1.upload-novalayer.com/files/6/2andwqmcch1zt3/10.png&lt;/a&gt; &lt;a href=&quot;\nhttp://server1.upload-novalayer.com/files/0/8j7pr3zlwbsixf/11.png&quot; rel=&quot;nofollow&quot; target=&quot;_NEW&quot;&gt;\nhttp://server1.upload-novalayer.com/files/0/8j7pr3zlwbsixf/11.png&lt;/a&gt; &lt;a href=&quot;\nhttp://server1.upload-novalayer.com/files/3/orti0kb75j7pnr/12.png&quot; rel=&quot;nofollow&quot; target=&quot;_NEW&quot;&gt;\nhttp://server1.upload-novalayer.com/files/3/orti0kb75j7pnr/12.png&lt;/a&gt; &lt;a href=&quot;\nhttp://server1.upload-novalayer.com/files/5/pvln5uk9ypllm4/13.png&quot; rel=&quot;nofollow&quot; target=&quot;_NEW&quot;&gt;\nhttp://server1.upload-novalayer.com/files/5/pvln5uk9ypllm4/13.png&lt;/a&gt;\n","torrent":{"xt":"urn:btih:e41758a6db865385a74893502239b590a4f4bee3","amp;dn":"Rockstar+-+DVDRip+-+720p+-+x264+-+%5BDDR%5D","amp;tr":["udp%3A%2F%2Ftracker.openbittorrent.com%3A80","udp%3A%2F%2Fopen.demonii.com%3A1337","udp%3A%2F%2Ftracker.coppersurfer.tk%3A6969","udp%3A%2F%2Fexodus.desync.com%3A6969"],"infoHash":"e41758a6db865385a74893502239b590a4f4bee3","infoHashBuffer":{"type":"Buffer","data":[228,23,88,166,219,134,83,133,167,72,147,80,34,57,181,144,164,244,190,227]},"announce":[],"urlList":[]}}