{"title":"Navy Seals Buds Class 234 1of6 Welcome to Buds DVDRip x264 [MVGr","uid":11009072,"size":704218669,"categoryP":"video","categoryS":"tv_shows","magnet":"?xt=urn:btih:ed114d7f625582b2457ee64559553bc33d5f6445&amp;dn=Navy+Seals+Buds+Class+234+1of6+Welcome+to+Buds+DVDRip+x264+%5BMVGr&amp;tr=udp%3A%2F%2Ftracker.openbittorrent.com%3A80&amp;tr=udp%3A%2F%2Fopen.demonii.com%3A1337&amp;tr=udp%3A%2F%2Ftracker.coppersurfer.tk%3A6969&amp;tr=udp%3A%2F%2Fexodus.desync.com%3A6969","seeders":11,"leechers":1,"uploader":"eztv","files":1,"time":1410307513,"description":"Help us by donating with Bitcoin: 1EZTVaGQ6UsjYJ9fwqGnd45oZ6HGT7WKZd\n\n#EZTV -&gt; To avoid fakes, ALWAYS check that the torrent was added by eztv. &lt;a href=&quot;\nhttps://eztv.it/&quot; rel=&quot;nofollow&quot; target=&quot;_NEW&quot;&gt;\nhttps://eztv.it/&lt;/a&gt;\n\nEpisode: Navy Seals Buds Class 234 1of6 Welcome to Buds DVDRip x264 [MVGroup org]\nScreenshots:\n\n\n","torrent":{"xt":"urn:btih:ed114d7f625582b2457ee64559553bc33d5f6445","amp;dn":"Navy+Seals+Buds+Class+234+1of6+Welcome+to+Buds+DVDRip+x264+%5BMVGr","amp;tr":["udp%3A%2F%2Ftracker.openbittorrent.com%3A80","udp%3A%2F%2Fopen.demonii.com%3A1337","udp%3A%2F%2Ftracker.coppersurfer.tk%3A6969","udp%3A%2F%2Fexodus.desync.com%3A6969"],"infoHash":"ed114d7f625582b2457ee64559553bc33d5f6445","infoHashBuffer":{"type":"Buffer","data":[237,17,77,127,98,85,130,178,69,126,230,69,89,85,59,195,61,95,100,69]},"announce":[],"urlList":[]}}